certbot_dns_navercloud/__init__.py
certbot_dns_navercloud/dns_navercloud.py
certbot_dns_navercloud-0.1.dist-info/LICENSE
certbot_dns_navercloud-0.1.dist-info/METADATA
certbot_dns_navercloud-0.1.dist-info/WHEEL
certbot_dns_navercloud-0.1.dist-info/entry_points.txt
certbot_dns_navercloud-0.1.dist-info/top_level.txt
certbot_dns_navercloud-0.1.dist-info/RECORD
