Metadata-Version: 2.1
Name: certbot-dns-navercloud
Version: 0.1
Summary: NaverCloud DNS Authenticator plugin for Certbot
Home-page: https://github.com/datamaker-kr/certbot-dns-navercloud
Author: datamaker
Author-email: developer@datamaker.io
License: MIT
Classifier: Programming Language :: Python :: 3
Classifier: License :: OSI Approved :: MIT License
Classifier: Operating System :: OS Independent
Requires-Python: >=3.6
License-File: LICENSE
Requires-Dist: certbot (>=1.10.0)
